auth_logger/__init__.py
auth_logger/apps.py
auth_logger/py.typed
auth_logger/signals/__init__.py
auth_logger/signals/handlers.py
auth_logger/tests.py
django_auth_logger-2.3.0.dist-info/LICENSE
django_auth_logger-2.3.0.dist-info/METADATA
django_auth_logger-2.3.0.dist-info/WHEEL
django_auth_logger-2.3.0.dist-info/RECORD
