Metadata-Version: 2.3
Name: django-auth-logger
Version: 2.3.0
Summary: A tiny project to log login attempts. Log them only to standard logging - not the database.
License: ISC
Author: thelab
Author-email: thelabdev@thelab.co
Requires-Python: >=3.11,<4.0
Classifier: License :: OSI Approved
Classifier: Programming Language :: Python :: 3
Classifier: Programming Language :: Python :: 3.11
Classifier: Programming Language :: Python :: 3.12
Classifier: Programming Language :: Python :: 3.13
Requires-Dist: Django (>=4.2)
Requires-Dist: django-ipware (>=7.0.1)
Project-URL: Homepage, https://gitlab.com/thelabnyc/django-auth-logger
Project-URL: Repository, https://gitlab.com/thelabnyc/django-auth-logger
